azure/mgmt/kubernetesconfiguration/privatelinkscopes/__init__.py
azure/mgmt/kubernetesconfiguration/privatelinkscopes/_configuration.py
azure/mgmt/kubernetesconfiguration/privatelinkscopes/_kubernetes_configuration_private_link_scopes_mgmt_client.py
azure/mgmt/kubernetesconfiguration/privatelinkscopes/_patch.py
azure/mgmt/kubernetesconfiguration/privatelinkscopes/_version.py
azure/mgmt/kubernetesconfiguration/privatelinkscopes/py.typed
azure/mgmt/kubernetesconfiguration/privatelinkscopes/_utils/__init__.py
azure/mgmt/kubernetesconfiguration/privatelinkscopes/_utils/serialization.py
azure/mgmt/kubernetesconfiguration/privatelinkscopes/aio/__init__.py
azure/mgmt/kubernetesconfiguration/privatelinkscopes/aio/_configuration.py
azure/mgmt/kubernetesconfiguration/privatelinkscopes/aio/_kubernetes_configuration_private_link_scopes_mgmt_client.py
azure/mgmt/kubernetesconfiguration/privatelinkscopes/aio/_patch.py
azure/mgmt/kubernetesconfiguration/privatelinkscopes/aio/operations/__init__.py
azure/mgmt/kubernetesconfiguration/privatelinkscopes/aio/operations/_patch.py
azure/mgmt/kubernetesconfiguration/privatelinkscopes/aio/operations/_private_endpoint_connections_operations.py
azure/mgmt/kubernetesconfiguration/privatelinkscopes/aio/operations/_private_link_resources_operations.py
azure/mgmt/kubernetesconfiguration/privatelinkscopes/aio/operations/_private_link_scopes_operations.py
azure/mgmt/kubernetesconfiguration/privatelinkscopes/models/__init__.py
azure/mgmt/kubernetesconfiguration/privatelinkscopes/models/_kubernetes_configuration_private_link_scopes_mgmt_client_enums.py
azure/mgmt/kubernetesconfiguration/privatelinkscopes/models/_models_py3.py
azure/mgmt/kubernetesconfiguration/privatelinkscopes/models/_patch.py
azure/mgmt/kubernetesconfiguration/privatelinkscopes/operations/__init__.py
azure/mgmt/kubernetesconfiguration/privatelinkscopes/operations/_patch.py
azure/mgmt/kubernetesconfiguration/privatelinkscopes/operations/_private_endpoint_connections_operations.py
azure_mgmt_kubernetesconfiguration_privatelinkscopes-1.0.0b1.dist-info/LICENSE
azure_mgmt_kubernetesconfiguration_privatelinkscopes-1.0.0b1.dist-info/METADATA
azure_mgmt_kubernetesconfiguration_privatelinkscopes-1.0.0b1.dist-info/WHEEL
azure_mgmt_kubernetesconfiguration_privatelinkscopes-1.0.0b1.dist-info/top_level.txt
azure_mgmt_kubernetesconfiguration_privatelinkscopes-1.0.0b1.dist-info/RECORD
